configgy/__init__.py
configgy/loader.py
configgy-0.1.1.dist-info/WHEEL
configgy-0.1.1.dist-info/METADATA
configgy-0.1.1.dist-info/RECORD
