Metadata-Version: 2.1
Name: configgy
Version: 0.1.1
Summary: A subtle config loader for python
Home-page: https://github.com/baniasbaabe/configgy
License: MIT
Keywords: ´config,yaml,json,toml,ini
Author: baniasbaabe
Author-email: banias@hotmail.de
Requires-Python: >=3.8,<4.0
Classifier: License :: OSI Approved :: MIT License
Classifier: Operating System :: OS Independent
Classifier: Programming Language :: Python :: 3
Classifier: Programming Language :: Python :: 3.10
Classifier: Programming Language :: Python :: 3.8
Classifier: Programming Language :: Python :: 3.9
Classifier: Topic :: Software Development :: Documentation
Classifier: Topic :: Software Development :: Libraries :: Python Modules
Classifier: Topic :: Software Development :: Quality Assurance
Requires-Dist: PyYAML (>=6.0,<7.0)
Requires-Dist: configparser (>=5.3.0,<6.0.0)
Requires-Dist: toml (>=0.10.2,<0.11.0)
Project-URL: Repository, https://github.com/baniasbaabe/configgy
